{"Shops": {"1": {"name": "alza.cz - sometimes bot policy problems", "titleIndex": [{"itemprop": "name"}], "priceIndex": [{"class": "price_withVat"}]}, "2": {"name": "answear.cz", "titleIndex": [{"id": "productPanel"}, {"class": "productPanelTop"}, {"class": "title"}], "priceIndex": [{"id": "productPanel"}, {"class": "productPanelTop"}, {"itemprop": "price"}]}, "3": {"name": "planetaher.cz", "titleIndex": [{"class": "last"}], "priceIndex": [{"id": "snippet--snPrice"}]}}, "Products": {"1": {"link": "https://answear.cz/2109948-tommy-hilfiger-boty.html", "time": ["2020-05-11 14:57:44", "2020-05-11 14:58:19", "2020-05-13 12:48:16", "2020-05-14 09:51:29", "2020-05-26 11:26:52", "2020-05-27 20:37:28", "2020-05-27 20:38:21", "2020-05-27 20:38:50"], "prices": [1899, 2201, 2099, 1699, 1899.0, 1899.0, 1899.0, 1899.0]}, "2": {"link": "https://answear.cz/1982228-calvin-klein-mikina.html", "time": ["2020-05-13 14:22:20", "2020-05-13 14:54:22", "2020-05-13 16:13:43", "2020-05-13 17:33:34", "2020-05-13 18:33:45", "2020-05-13 21:17:35", "2020-05-28 16:59:47", "2020-05-28 18:04:40"], "prices": [1699.0, 1699.0, 1699.0, 1699.0, 1699.0, 1699.0, 1499.0, 1499.0]}, "3": {"link": "https://www.alza.cz/stx-kn95-5ks-d5818509.htm", "time": ["2020-05-18 12:11:52"], "prices": [299.0]}, "4": {"link": "https://www.alza.cz/repasovany-iphone-7?dq=5830982", "time": ["2020-05-18 12:11:55"], "prices": [7499.0]}, "5": {"link": "https://answear.cz/1902783-adidas-originals-detske-boty-stan-smith-cf.html", "time": ["2020-05-28 17:23:50", "2020-05-28 17:23:53"], "prices": [1049.0, 1049.0]}, "6": {"link": "https://answear.cz/2125465-calvin-klein-jeans-kosile.html", "time": ["2020-05-28 18:04:40", "2020-05-28 18:04:43", "2020-05-28 18:21:25"], "prices": [1799.0, 1799.0, 1799.0]}}, "Users": {"1": {"email": "vavasyukova@edu.hse.ru", "products": [1], "priceToInform": [2000]}, "2": {"email": "cere06@gmail.com", "products": [2], "priceToInform": [1050.0]}, "3": {"email": "novacek.ond@gmail.com", "products": [2, 6], "priceToInform": [1000.0, 2000.0]}, "4": {"email": "something@mail.ru", "products": [], "priceToInform": []}, "5": {"email": "thomasstein@mail.ru", "products": [3, 4], "priceToInform": [300.0, 7400.0]}, "6": {"email": "xnovace3@mendelu.cz", "products": [5], "priceToInform": [1999.0]}}}